LICENSE
MANIFEST.in
README.md
readthedocs.yml
requirements-extras.txt
requirements-tests.txt
requirements.txt
setup.py
depends/Makefile
depends/class-v2.6.1.tar.gz
depends/class.cfg
depends/install_class.sh
pyRSD/__init__.py
pyRSD/gcl.i
pyRSD/pygcl.py
pyRSD/version.py
pyRSD.egg-info/PKG-INFO
pyRSD.egg-info/SOURCES.txt
pyRSD.egg-info/dependency_links.txt
pyRSD.egg-info/entry_points.txt
pyRSD.egg-info/not-zip-safe
pyRSD.egg-info/requires.txt
pyRSD.egg-info/top_level.txt
pyRSD/_gcl/cpp/ClassEngine.cpp
pyRSD/_gcl/cpp/ClassParams.cpp
pyRSD/_gcl/cpp/Common.cpp
pyRSD/_gcl/cpp/CorrelationFunction.cpp
pyRSD/_gcl/cpp/Cosmology.cpp
pyRSD/_gcl/cpp/Datafile.cpp
pyRSD/_gcl/cpp/DiscreteQuad.cpp
pyRSD/_gcl/cpp/FortranFFTLog.cpp
pyRSD/_gcl/cpp/Imn.cpp
pyRSD/_gcl/cpp/ImnOneLoop.cpp
pyRSD/_gcl/cpp/Jmn.cpp
pyRSD/_gcl/cpp/Kaiser.cpp
pyRSD/_gcl/cpp/Kmn.cpp
pyRSD/_gcl/cpp/LinearPS.cpp
pyRSD/_gcl/cpp/MyFFTLog.cpp
pyRSD/_gcl/cpp/NonlinearPS.cpp
pyRSD/_gcl/cpp/OneLoopPS.cpp
pyRSD/_gcl/cpp/PowerSpectrum.cpp
pyRSD/_gcl/cpp/Quadrature.cpp
pyRSD/_gcl/cpp/SpecialFunctions.cpp
pyRSD/_gcl/cpp/Spline.cpp
pyRSD/_gcl/cpp/Timer.cpp
pyRSD/_gcl/cpp/ZeldovichCF.cpp
pyRSD/_gcl/cpp/ZeldovichPS.cpp
pyRSD/_gcl/cpp/parray.cpp
pyRSD/_gcl/cpp/pstring.cpp
pyRSD/_gcl/extern/FrankenEmu/include/corrlengths.h
pyRSD/_gcl/extern/FrankenEmu/include/corrlengths_noh.h
pyRSD/_gcl/extern/FrankenEmu/include/design.h
pyRSD/_gcl/extern/FrankenEmu/include/design_noh.h
pyRSD/_gcl/extern/FrankenEmu/include/kemu.h
pyRSD/_gcl/extern/FrankenEmu/include/ksim.h
pyRSD/_gcl/extern/FrankenEmu/include/meansd.h
pyRSD/_gcl/extern/FrankenEmu/include/meansd_noh.h
pyRSD/_gcl/extern/FrankenEmu/include/pcbasis.h
pyRSD/_gcl/extern/FrankenEmu/include/pcbasis_noh.h
pyRSD/_gcl/extern/FrankenEmu/include/pcweights.h
pyRSD/_gcl/extern/FrankenEmu/include/pcweights_noh.h
pyRSD/_gcl/extern/FrankenEmu/include/precisions.h
pyRSD/_gcl/extern/FrankenEmu/include/precisions_noh.h
pyRSD/_gcl/extern/FrankenEmu/src/emu.c
pyRSD/_gcl/extern/FrankenEmu/src/emu_noh.c
pyRSD/_gcl/extern/FrankenEmu/src/hubble.c
pyRSD/_gcl/extern/fftlog/cdgamma.f
pyRSD/_gcl/extern/fftlog/drfftb.f
pyRSD/_gcl/extern/fftlog/drfftf.f
pyRSD/_gcl/extern/fftlog/drffti.f
