Metadata-Version: 2.1
Name: pyRSD
Version: 0.1.19
Summary: Accurate predictions for the clustering of galaxies in redshift-space in Python
Home-page: UNKNOWN
Maintainer: Nick Hand
Maintainer-email: nicholas.adam.hand@gmail.com
License: GPL3
Platform: UNKNOWN
Provides-Extra: test
Provides-Extra: tests
Provides-Extra: extras
Provides-Extra: full
